docution/__init__.py
docution/cli.py
docution/documenter.py
docution/notion_api.py
docution/packer.py
docution/sphinx/__init__.py
docution/sphinx/ast.py
docution/sphinx/parser.py
example/__init__.py
docution-0.0.2.dist-info/METADATA
docution-0.0.2.dist-info/WHEEL
docution-0.0.2.dist-info/entry_points.txt
docution-0.0.2.dist-info/top_level.txt
docution-0.0.2.dist-info/RECORD
