Metadata-Version: 2.1
Name: docution
Version: 0.0.2
Summary: Auto-document your API reference on Notion.
Home-page: https://github.com/astariul/docution
Author: Nicolas REMOND
Author-email: nicolas@remond.co
License: UNKNOWN
Platform: UNKNOWN
Classifier: Programming Language :: Python :: 3.6
Classifier: Operating System :: OS Independent
Requires-Python: >=3.6
Requires-Dist: notion-client (==0.4.*)
Requires-Dist: docstring-parser (==0.7.*)
Requires-Dist: click (==8.0.*)
